pyllsp/__init__.py
pyllsp/lsp.py
python_llsp-1.0.2.dist-info/LICENSE
python_llsp-1.0.2.dist-info/METADATA
python_llsp-1.0.2.dist-info/WHEEL
python_llsp-1.0.2.dist-info/entry_points.txt
python_llsp-1.0.2.dist-info/RECORD
