Metadata-Version: 2.3
Name: python-llsp
Version: 1.0.2
Summary: 
License: GPLv3
Author: Luã Bida Vacaro
Author-email: luabidaa@gmail.com
Requires-Python: >=3.9,<3.13
Classifier: License :: Other/Proprietary License
Classifier: Programming Language :: Python :: 3
Classifier: Programming Language :: Python :: 3.9
Classifier: Programming Language :: Python :: 3.10
Classifier: Programming Language :: Python :: 3.11
Classifier: Programming Language :: Python :: 3.12
Requires-Dist: importlib-metadata (>=8.6.1,<9.0.0)
Requires-Dist: jedi (>=0.19.2,<0.20.0)
Requires-Dist: pygls (>=2.0.0a1)
